taxi_ops_backend/__init__.py
taxi_ops_backend/custom_error.py
taxi_ops_backend/database.py
taxi_ops_backend/database_management.py
taxi_ops_backend/model.py
taxi_ops_backend/operation_management.py
taxi_ops_backend/taxi_driver_management.py
taxi_ops_backend/taxi_ops_logger.py
taxi_ops_backend/user_management.py
taxi_ops_backend-0.1.5.dist-info/METADATA
taxi_ops_backend-0.1.5.dist-info/WHEEL
taxi_ops_backend-0.1.5.dist-info/top_level.txt
taxi_ops_backend-0.1.5.dist-info/RECORD
